{
    "submit": "送信",
    "siteview": "日ブラウズ:",
    "siteview1": "合計ブラウズ数:",
    "jizhumima": "パスワードを覚える",
    "zidongdenglu": "自動ログイン",
    "username": "ユーザー名",
    "userpass": "パスワード",
    "welcome": "お帰りなさい~",
    "settingok": "設定 OK~",
    "saveok": "保存 OK~",
    "fabuok": "リリースOK~",
    "submitok": "コメントOK~",
    "deleteok": "クリアOK~",
    "deletimgeok": "削除 OK~",
    "logoutok": "抹消 OK~",
    "20sres": "20(i)cooling~",
    "loginnull": "ユーザー名パスワード必須",
    "loginerror": "ユーザ名パスワードエラー",
    "home": "表紙",
    "uploadpic": "画像追加",
    "avatartitle": "こんにちは~",
    "addpost": "公開内容",
    "editpost": "コンテンツの編集",
    "addposts": "新しいコンテンツの作成",
    "fabu": "パブリッシュ",
    "fabuyu": "公開先:",
    "zan": "いいね:",
    "ci": "次",
    "youmap": "現在の位置を入力",
    "allview": "公開する",
    "picture": "図鑑",
    "message": "掲示",
    "null": "無",
    "yincang": "******@***.***",
    "allmessage": "すべてのメッセージを表示しました",
    "deletemessage": "空伝言板",
    "deletemessageok": "伝言板を空にするのか。確認してください。",
    "about": "概要",
    "edit": "編集",
    "delete": "削除",
    "chakan": "表示",
    "deletepost": "投稿を削除しますか?",
    "introduction": "ジェーン介",
    "nickname": "網 人:",
    "niming": "匿 名",
    "gender": "性 别:",
    "age": "年の齢:",
    "vocation": "職業:",
    "sideline": "副 业:",
    "company": "公 司:",
    "city": "所在地:",
    "hometown": "故郷:",
    "email": "郵便ボックス:",
    "aboutme": "個人的な説明:",
    "social": "社の交:",
    "socials": "通 訊:",
    "platform": "平 台:",
    "more": "もっと多い",
    "hobby": "趣味嗜好:",
    "skill": "技 が:",
    "explain": "追加の説明:",
    "siteSet_sett": "ウェブサイトの設定",
    "siteSet_logo": "サイトロゴ",
    "siteSes_logo": "掲載 favicon 16x16.ico。",
    "siteSet_keys": "かんけい語&nbsp;：",
    "siteSes_keys": "検索エンジン最適化のために、キーワード同士を「,」で区切ってください。",
    "siteSet_desc": "描&nbsp;&nbsp;&nbsp;&nbsp;写&nbsp;&nbsp;&nbsp;：",
    "siteSes_desc": "記述は検索エンジン最適化のために用いられ、検索結果に示される。",
    "siteSet_sina": "サイト名",
    "siteSes_sina": "ウェブサイトに素敵な名前を付けて、タブに表示しましょう。",
    "siteSet_sige": "まえに",
    "siteSes_sige": "まえに \"-\" , \"|\" ，あるいは別の句読点を使って分割に合う。",
    "siteSet_tizo": "タイムゾーン設定:",
    "siteSes_tizo": "タイムゾーンを修正して、あなたに対応する地域を設定して、デフォルトアジア/上海。",
    "siteSet_ruyo": "漏れがあればフィードバックしてください",
    "siteSet_ponu": "たとえば文章の数：",
    "siteSes_ponu": "1回に載せる記事の数、多い記事は載せる速度に影響します。",
    "siteSet_lang": "ウェブサイト言語：",
    "siteSes_lang": "サイトのグローバル言語を設定し、言語ファイルを自分で変更できる。",
    "siteSet_them": "外観設定",
    "siteSet_toco": "トップバーの色:",
    "siteSes_toco": "バイナリカラー「#ccc」またはグラデーション “linear-gradient()”。",
    "siteSet_tomo": "ハードルがぼやけている:",
    "siteSes_tomo": "この場合は、色に透明度をつけるか、空にします。",
    "siteSet_toma": "メインカラー：",
    "siteSes_toma": "バイナリのカラーコードを記入し、サイト全体の色を決めます。",
    "siteSet_baim": "背景画像",
    "siteSes_baim": "1:1の正方形の背景をアップロードし、アップロード背景図を優先して表示します。",
    "siteSet_gere": "個人情報",
    "siteSet_geim": "个人头像個人のアイコン",
    "siteSes_geim": "1:1の正方形の画像をアップロードし、アップロードされた画像を優先的に表示します。",
    "siteSet_nina": "名&nbsp;&nbsp;&nbsp;&nbsp;称&nbsp;&nbsp;&nbsp;：",
    "siteSes_nina": "この名称はサイト名と同一ではなく、箇人としてのみ表示されます。",
    "siteSet_augr": "箇性署名：",
    "siteSes_augr": "箇性署名、ユーザー名の下に表示される小さな文字列。",
    "siteSet_qrco": "qrコード",
    "siteSes_qrco": "qrコード画像をアップロードすると、アップロードしたqrコードを優先的に表示します。",
    "siteSet_maps": "デフォルトアドレス:",
    "siteSes_maps": "送信にはデフォルトアドレスを優先的に使用する。送信時に個別に変更することができます。",
    "siteSet_emal": "メール：",
    "siteSes_emal": "管理者がアラートを受信するメールアドレスを設定し、自分のメールアドレスを持参することを推奨します。",
    "siteSet_lose": "ログイン設定",
    "siteSet_user": "登録名：",
    "siteSes_user": "バックグラウンドログインのためのログイン名は、アルファベットを使用することをお勧めします。",
    "siteSet_pass": "パスワード：",
    "siteSes_pass": "バックグラウンドにログインするためのパスワードは、復雑なものがおすすめです。",
    "siteSet_pasd": "パスワードを確認する",
    "siteSes_pasd": "パスワードを再度入力して、2回入力した値が同じであることを確認してください。",
    "siteSet_ohse": "その他の設定",
    "siteSet_fixe": "メニューバー",
    "siteSet_zhid": "ねんせい",
    "siteSes_fixe": "画面上部に表示され、消えずに表示されます。",
    "siteSet_robo": "Robotはよじ登り禁止",
    "siteSet_off": "無効",
    "siteSes_robo": "検索エンジンがウェブページをよじ登り、robotプロトコルを生成することを禁止する。",
    "siteSet_time": "時間書式：",
    "siteSet_setime": "時間フォーマットの入力",
    "siteSes_time": "時刻フォーマット、Ymd H:iは年月日を表す。",
    "siteSes_tity": "示例：Y-m-d H:i",
    "siteSet_weih": "メンテナンスモード",
    "siteSet_log1": "visitアクセスログの削除",
    "siteSet_log2": "loginログインログの削除",
    "siteSes_log1": "アクセスログのデフォルト値が100 Mbより大きいと、レコードが停止します。",
    "siteSes_log2": "ログインログに異常ログインしたipアドレスが記録されます。",
    "deletebackground": "背景を削除しますか?確認してください。",
    "deleteatavar": "アイコンを削除しますか?確認してください。",
    "deleteqrcode": "QRコードを削除しますか?確認してください。",
    "deletevisit": "アクセスログを削除しますか?確認してください。",
    "deletelogin": "ログインログを削除しますか?確認してください。",
    "siteSet_on": "オン",
    "siteSes_weih": "メンテナンスモードへの対応は見合わせておりますが、追ってアップデートを行います。",
    "siteSet_save": "きおく",
    "siteSet_submit": "提出する",
    "siteSet_bain": "トップページに戻る",
    "siteSet_upda": "更新をチェックする",
    "siteSet_help": "助けを得る",
    "siteSet_fank": "質問のフィードバック",
    "message_nik": "ニックネーム",
    "message_mal": "メールボックス",
    "message_mes": "メッセージの入力",
    "notfound": "エラー!",
    "nocontent": "内容なし",
    "nocontents": "内容なし",
    "addmore": "クリックして追加",
    "loginpage": "バックグラウンドログイン",
    "liuyancuowu": "機密文字!",
    "lightbox": "大図モード",
    "zoomin": "拡大",
    "zoomout": "縮小",
    "maximise": "完全",
    "refresh": "回転",
    "horizontal": "反転",
    "fabuzhong": "公開中...",
    "tijiaozhong": "コミット中...",
    "login": "LOGIN",
    "installError": "情報に誤りがある!",
    "linkDBerror": "データベースに接続できません!",
    "tableError": "データ例外の作成! ",
    "installError01": "エラーメッセージのチェックでは、次のことができます。<br>1.サーバーアドレスが間違っているかどうかを確認し、デフォルトlocalhost。br>2.データベースのユーザー名パスワードが正しいかどうかを確認します。<br>3.データベース名はMySQLに作成しておく必要があります。<br><br>失敗した場合は管理者に連絡してください。<br><br>rockstali@outlook.com",
    "yourname": "あなたのログイン名",
    "linkOK01": "ユーザー名のパスワードを覚え、バックグラウンドに入るとパスワードを変更できます。",
    "linkOK02": "フォームの作成に成功しました!",
    "linkOK04": "私をクリックしてトップページに行きましょう~",
    "emailmessagesubject": "誰かが君にメッセージを残した",
    "emailmessagetite": "タイトル:",
    "emailmessagecontent1": "情報:",
    "emailmessagecontent2": "内容:",
    "emailmessagecontent3": "から",
    "emailmessagecontent4": "メール通知",
    "emailmessagecontent5": "詳細",
    "emailmessageheaders": "伝言を残す"
}